femmt/__init__.py
femmt/component.py
femmt/constants.py
femmt/data.py
femmt/drawing.py
femmt/dtos.py
femmt/enumerations.py
femmt/functions.py
femmt/functions_drawing.py
femmt/functions_model.py
femmt/functions_reluctance.py
femmt/functions_topologies.py
femmt/hpc.py
femmt/logparser.py
femmt/mesh.py
femmt/model.py
femmt/reluctance.py
femmt/electro_magnetic/fields.pro
femmt/electro_magnetic/fields_time.pro
femmt/electro_magnetic/ind_axi_python_controlled.pro
femmt/electro_magnetic/ind_axi_python_controlled_time.pro
femmt/electro_magnetic/solver.pro
femmt/electro_magnetic/solver_time.pro
femmt/electro_magnetic/values.pro
femmt/electro_magnetic/values_time.pro
femmt/electro_magnetic/Strands_Coefficients/cell.geo
femmt/electro_magnetic/Strands_Coefficients/cell.pro
femmt/electro_magnetic/Strands_Coefficients/cell_dat.pro
femmt/electro_magnetic/Strands_Coefficients/unused/cell_hexa_circ.geo
femmt/electro_magnetic/Strands_Coefficients/unused/cell_square_circ.geo
femmt/examples/__init__.py
femmt/examples/advanced_inductor_air_gap_sweep.py
femmt/examples/advanced_inductor_sweep.py
femmt/examples/advanced_sto.py
femmt/examples/basic_inductor.py
femmt/examples/basic_inductor_excitation_sweep.py
femmt/examples/basic_inductor_foil_vertical.py
femmt/examples/basic_inductor_time_domain.py
femmt/examples/basic_split_windings.py
femmt/examples/basic_transformer.py
femmt/examples/basic_transformer_5_windings.py
femmt/examples/basic_transformer_6_windings.py
femmt/examples/basic_transformer_center_tapped.py
femmt/examples/basic_transformer_excitation_sweep.py
femmt/examples/basic_transformer_integrated.py
femmt/examples/basic_transformer_interleaved.py
femmt/examples/basic_transformer_n_winding.py
femmt/examples/basic_transformer_stacked.py
femmt/examples/basic_transformer_stacked_center_tapped.py
femmt/examples/basic_transformer_three_winding.py
femmt/examples/basic_transformer_three_winding_time_domain.py
femmt/examples/basic_transformer_time_domain.py
femmt-0.5.4.dist-info/LICENSE
femmt-0.5.4.dist-info/METADATA
femmt-0.5.4.dist-info/WHEEL
femmt-0.5.4.dist-info/top_level.txt
femmt-0.5.4.dist-info/RECORD
