Metadata-Version: 2.1
Name: femmt
Version: 0.5.4
Summary: FEM Magnetics Toolbox
Home-page: https://github.com/upb-lea/FEM_Magnetics_Toolbox
Author: LEA - Uni Paderborn
Author-email: upblea@mail.upb.de
License: GNU General Public License v3
Project-URL: Documentation, https://upb-lea.github.io/FEM_Magnetics_Toolbox/main/intro.html
Project-URL: Source Code, https://github.com/upb-lea/FEM_Magnetics_Toolbox
Keywords: femmt
Classifier: Development Status :: 3 - Alpha
Classifier: Intended Audience :: Developers
Classifier: License :: OSI Approved :: GNU General Public License v3 (GPLv3)
Classifier: Natural Language :: English
Classifier: Topic :: Scientific/Engineering
Classifier: Programming Language :: Python :: 3
Classifier: Programming Language :: Python :: 3.10
Classifier: Programming Language :: Python :: 3.11
Classifier: Programming Language :: Python :: 3.12
Classifier: Operating System :: Microsoft :: Windows
Classifier: Operating System :: POSIX :: Linux
Classifier: Environment :: MacOS X
Requires-Python: >=3.10
License-File: LICENSE
Requires-Dist: pandas ~=2.2.1
Requires-Dist: numpy ~=1.26.0
Requires-Dist: matplotlib ~=3.8.0
Requires-Dist: gmsh >=4.13.1
Requires-Dist: onelab >=1.0
Requires-Dist: scipy ~=1.12.0
Requires-Dist: pytest
Requires-Dist: pycodestyle
Requires-Dist: PyQt5 >=5.15.6
Requires-Dist: mplcursors >=0.5.1
Requires-Dist: deepdiff >=6.2.1
Requires-Dist: materialdatabase ==0.3.0
Requires-Dist: optuna
Requires-Dist: plotly
